code_rag/__init__.py
code_rag/cli.py
code_rag/config.py
code_rag/database.py
code_rag/embeddings.py
code_rag/indexer.py
code_rag/search.py
code_rag/tree_sitter_utils.py
qwen_rag-0.1.0.dist-info/licenses/LICENSE
qwen_rag-0.1.0.dist-info/METADATA
qwen_rag-0.1.0.dist-info/WHEEL
qwen_rag-0.1.0.dist-info/entry_points.txt
qwen_rag-0.1.0.dist-info/top_level.txt
qwen_rag-0.1.0.dist-info/RECORD
