Metadata-Version: 2.4
Name: qwen-rag
Version: 0.1.0
Summary: A powerful RAG system for querying code repositories using tree-sitter parsing, LanceDB vector storage, and Qwen models
Home-page: https://github.com/yourusername/QwenRag
Author: Qwen RAG Contributors
Author-email: 
Project-URL: Bug Reports, https://github.com/yourusername/QwenRag/issues
Project-URL: Source, https://github.com/yourusername/QwenRag
Project-URL: Documentation, https://github.com/yourusername/QwenRag#readme
Keywords: rag,code search,embeddings,vector database,qwen,tree-sitter,semantic search
Classifier: Development Status :: 4 - Beta
Classifier: Intended Audience :: Developers
Classifier: License :: OSI Approved :: MIT License
Classifier: Operating System :: OS Independent
Classifier: Programming Language :: Python :: 3
Classifier: Programming Language :: Python :: 3.9
Classifier: Programming Language :: Python :: 3.10
Classifier: Programming Language :: Python :: 3.11
Classifier: Programming Language :: Python :: 3.12
Classifier: Topic :: Software Development :: Libraries :: Python Modules
Classifier: Topic :: Scientific/Engineering :: Artificial Intelligence
Classifier: Topic :: Text Processing :: Indexing
Requires-Python: >=3.9
License-File: LICENSE
Requires-Dist: lancedb>=0.12.0
Requires-Dist: tree-sitter>=0.20.0
Requires-Dist: tree-sitter-python>=0.20.0
Requires-Dist: tree-sitter-javascript>=0.20.0
Requires-Dist: tree-sitter-typescript>=0.20.0
Requires-Dist: tree-sitter-java>=0.20.0
Requires-Dist: tree-sitter-cpp>=0.20.0
Requires-Dist: tree-sitter-c>=0.20.0
Requires-Dist: tree-sitter-c-sharp>=0.20.0
Requires-Dist: tree-sitter-rust>=0.20.0
Requires-Dist: tree-sitter-go>=0.20.0
Requires-Dist: openai>=1.0.0
Requires-Dist: click>=8.0.0
Requires-Dist: pydantic>=2.0.0
Requires-Dist: tqdm>=4.60.0
Requires-Dist: pathspec>=0.11.0
Requires-Dist: gitignore-parser>=0.1.0
Requires-Dist: PyYAML
Dynamic: author
Dynamic: classifier
Dynamic: description
Dynamic: description-content-type
Dynamic: home-page
Dynamic: keywords
Dynamic: license-file
Dynamic: project-url
Dynamic: requires-dist
Dynamic: requires-python
Dynamic: summary
